mc_trimmer/__init__.py
mc_trimmer/__main__.py
mc_trimmer/__version__.py
mc_trimmer/cli.py
mc_trimmer/entities.py
mc_trimmer/main.py
mc_trimmer/primitives.py
mc_trimmer/regions.py
mc_trimmer/submodule/__init__.py
mc_trimmer/submodule/subcomponent.py
mc_trimmer-0.1.2.dist-info/LICENSE
mc_trimmer-0.1.2.dist-info/METADATA
mc_trimmer-0.1.2.dist-info/WHEEL
mc_trimmer-0.1.2.dist-info/entry_points.txt
mc_trimmer-0.1.2.dist-info/top_level.txt
mc_trimmer-0.1.2.dist-info/RECORD
