Metadata-Version: 2.1
Name: mc-trimmer
Version: 0.1.2
Author: Dw4lt
License: MIT
Requires-Python: >=3.11
License-File: LICENSE
Requires-Dist: NBT >=1.5.1
Requires-Dist: multiprocess >=0.70.15
